<setup>
  <block title="Initial Setup Configuration">
    <text>Setup page with custom endpoints and user details</text>
  </block>

  <block title="User Information" endpoint="mycustom/customendpoint" entity="onetime_setup">

      <input field="appname">
        <label>Enter Splunk App name</label>
        <type>text</type>
      </input>

      <input field="username">
        <label>Enter Username</label>
        <type>text</type>
      </input>

      <input field="password">
        <label>Enter Password</label>
        <type>text</type>
      </input>

  </block>

  <block title="Splunk Instance Endpoints" endpoint="mycustom/customendpoint" entity="onetime_setup">

    <input field="my_bool_variable">
      <label>Select this if you want to use boolean</label>
      <type>bool</type>
    </input>

    <input field="host">
      <label>Enter the hostname or IP Address</label>
      <type>text</type>
    </input>

    <input field="port">
      <label>Enter the port number</label>
      <type>text</type>
    </input>

  </block>

</setup>